tc_data_tools
